bartz/.DS_Store
bartz/BART.py
bartz/__init__.py
bartz/_version.py
bartz/debug.py
bartz/grove.py
bartz/jaxext/__init__.py
bartz/jaxext/_autobatch.py
bartz/jaxext/scipy/__init__.py
bartz/jaxext/scipy/special.py
bartz/jaxext/scipy/stats.py
bartz/mcmcloop.py
bartz/mcmcstep.py
bartz/prepcovars.py
bartz-0.7.0.dist-info/WHEEL
bartz-0.7.0.dist-info/METADATA
bartz-0.7.0.dist-info/RECORD
