Metadata-Version: 2.4
Name: bartz
Version: 0.7.0
Summary: Super-fast BART (Bayesian Additive Regression Trees) in Python
Author: Giacomo Petrillo
Author-email: Giacomo Petrillo <info@giacomopetrillo.com>
License-Expression: MIT
Requires-Dist: equinox>=0.12.2
Requires-Dist: jax>=0.5.3
Requires-Dist: jaxtyping>=0.3.2
Requires-Dist: numpy>=1.25.2
Requires-Dist: scipy>=1.11.4
Requires-Python: >=3.10
Project-URL: Documentation, https://gattocrucco.github.io/bartz/docs-dev
Project-URL: Homepage, https://github.com/Gattocrucco/bartz
Project-URL: Issues, https://github.com/Gattocrucco/bartz/issues
